odoo/addons/l10n_fr_chorus_facturx/README.rst
odoo/addons/l10n_fr_chorus_facturx/__init__.py
odoo/addons/l10n_fr_chorus_facturx/__manifest__.py
odoo/addons/l10n_fr_chorus_facturx/i18n/fr.po
odoo/addons/l10n_fr_chorus_facturx/i18n/l10n_fr_chorus_factur-x.pot
odoo/addons/l10n_fr_chorus_facturx/i18n/l10n_fr_chorus_facturx.pot
odoo/addons/l10n_fr_chorus_facturx/i18n/nb_NO.po
odoo/addons/l10n_fr_chorus_facturx/models/__init__.py
odoo/addons/l10n_fr_chorus_facturx/models/account_move.py
odoo/addons/l10n_fr_chorus_facturx/models/chorus_flow.py
odoo/addons/l10n_fr_chorus_facturx/models/company.py
odoo/addons/l10n_fr_chorus_facturx/readme/CONFIGURE.rst
odoo/addons/l10n_fr_chorus_facturx/readme/CONTRIBUTORS.rst
odoo/addons/l10n_fr_chorus_facturx/readme/DESCRIPTION.rst
odoo/addons/l10n_fr_chorus_facturx/readme/USAGE.rst
odoo/addons/l10n_fr_chorus_facturx/static/description/icon.png
odoo/addons/l10n_fr_chorus_facturx/static/description/index.html
odoo14_addon_l10n_fr_chorus_facturx-14.0.2.0.0.dist-info/METADATA
odoo14_addon_l10n_fr_chorus_facturx-14.0.2.0.0.dist-info/WHEEL
odoo14_addon_l10n_fr_chorus_facturx-14.0.2.0.0.dist-info/top_level.txt
odoo14_addon_l10n_fr_chorus_facturx-14.0.2.0.0.dist-info/RECORD
