Metadata-Version: 2.1
Name: odoo14-addon-l10n_fr_chorus_facturx
Version: 14.0.2.0.0
Summary: Generate Chorus-compliant Factur-X invoices
Home-page: https://github.com/OCA/l10n-france
Author: Akretion,Odoo Community Association (OCA)
Author-email: support@odoo-community.org
License: AGPL-3
Classifier: Programming Language :: Python
Classifier: Framework :: Odoo
Classifier: Framework :: Odoo :: 14.0
Classifier: License :: OSI Approved :: GNU Affero General Public License v3
Requires-Python: >=3.6
Requires-Dist: odoo14-addon-l10n-fr-account-invoice-facturx
Requires-Dist: odoo14-addon-l10n-fr-chorus-account
Requires-Dist: odoo <14.1dev,>=14.0a
